{
    "BJ": "101010100",
    "SH": "101020100",
    "TJ": "101030100",
    "CQ": "101040100",
    "SD": {
        "JN": "101120101",
        "QD": "101120201",
        "ZZ": "101121401",
        "ZP": "101121107"
    },
    "SX": {
        "XA": "101110101",
        "YL": "101110401",
        "HZ": "101110801"
    },
    "JX": {
        "NC": "101240101",
        "GZ": "101240701"
    },
    "AH": {
        "HF": "101220101",
        "CZ": "101221701"
    },
    "YN": {
        "KM": "101290101",
        "YX": "101290701"
    },
    "JL": {
        "CC": "101060101",
        "JL": "101060201"
    },
    "XJ": {
        "WLMQ": "101130101",
        "SW": "101131107"
    }
    
}
